<annotation>
	<folder>my-project-name</folder>
	<filename>1-28.jpg</filename>
	<path>/my-project-name/1-28.jpg</path>
	<source>
		<database>Unspecified</database>
	</source>
	<size>
		<width>1280</width>
		<height>960</height>
		<depth>3</depth>
	</size>
	<object>
		<name>Turn Left</name>
		<pose>Unspecified</pose>
		<truncated>0</truncated>
		<difficult>0</difficult>
		<bndbox>
			<xmin>77</xmin>
			<ymin>503</ymin>
			<xmax>262</xmax>
			<ymax>658</ymax>
		</bndbox>
	</object>
	<object>
		<name>Give Way</name>
		<pose>Unspecified</pose>
		<truncated>0</truncated>
		<difficult>0</difficult>
		<bndbox>
			<xmin>67</xmin>
			<ymin>288</ymin>
			<xmax>304</xmax>
			<ymax>493</ymax>
		</bndbox>
	</object>
	<object>
		<name>Stop</name>
		<pose>Unspecified</pose>
		<truncated>0</truncated>
		<difficult>0</difficult>
		<bndbox>
			<xmin>582</xmin>
			<ymin>647</ymin>
			<xmax>624</xmax>
			<ymax>692</ymax>
		</bndbox>
	</object>
	<object>
		<name>Stop</name>
		<pose>Unspecified</pose>
		<truncated>0</truncated>
		<difficult>0</difficult>
		<bndbox>
			<xmin>180</xmin>
			<ymin>664</ymin>
			<xmax>238</xmax>
			<ymax>716</ymax>
		</bndbox>
	</object>
</annotation>